README.rst
setup.py
mk60/__init__.py
mk60/app.py
mk60.egg-info/PKG-INFO
mk60.egg-info/SOURCES.txt
mk60.egg-info/dependency_links.txt
mk60.egg-info/entry_points.txt
mk60.egg-info/top_level.txt