Metadata-Version: 1.1
Name: mk60
Version: 0.1a1
Summary: Utility assisting in creation of D3-28 tapes
Home-page: https://github.com/xoiss/mk60
Author: Alexander A. Strelets
Author-email: StreletsAA@gmail.com
License: Public Domain
Download-URL: https://github.com/xoiss/mk60
Platform: Linux
Platform: Windows
Classifier: Development Status :: 3 - Alpha
Classifier: Environment :: Console
Classifier: Intended Audience :: Science/Research
Classifier: License :: CC0 1.0 Universal (CC0 1.0) Public Domain Dedication
Classifier: Natural Language :: English
Classifier: Operating System :: POSIX :: Linux
Classifier: Operating System :: Microsoft :: Windows
Classifier: Programming Language :: Python :: 2.7
Classifier: Programming Language :: Python :: 3.4
Classifier: Topic :: Multimedia :: Sound/Audio :: Sound Synthesis
